rec_to_binaries/__init__.py
rec_to_binaries/adjust_timestamps.py
rec_to_binaries/binary_utils.py
rec_to_binaries/core.py
rec_to_binaries/create_system_time.py
rec_to_binaries/read_binaries.py
rec_to_binaries/trodes_data.py
rec_to_binaries-0.7.5.dist-info/LICENSE
rec_to_binaries-0.7.5.dist-info/METADATA
rec_to_binaries-0.7.5.dist-info/WHEEL
rec_to_binaries-0.7.5.dist-info/top_level.txt
rec_to_binaries-0.7.5.dist-info/RECORD
