Metadata-Version: 2.1
Name: rec-to-binaries
Version: 0.7.5
Summary: Covert SpikeGadgets rec files to binaries
Home-page: https://github.com/LorenFrankLab/rec_to_binaries
Author: Eric Denovellis, Daniel Liu
Author-email: Eric.Denovellis@ucsf.edu
License: MIT
Requires-Python: >=3.6
License-File: LICENSE
Requires-Dist: numpy
Requires-Dist: pandas
Requires-Dist: scipy
